README.rst
setup.py
DrafterPy.egg-info/PKG-INFO
DrafterPy.egg-info/SOURCES.txt
DrafterPy.egg-info/dependency_links.txt
DrafterPy.egg-info/top_level.txt
lib/__init__.py
lib/blueprint.py
src/drafterpy.c