Metadata-Version: 1.1
Name: DrafterPy
Version: 0.1.2
Summary: Python bindings for libdrafter
Home-page: https://github.com/menecio/drafterpy
Author: menecio
Author-email: aristobulo@gmail.com
License: MIT License
Keywords: python3,api-blueprint
Platform: any
Classifier: Development Status :: 3 - Alpha
Classifier: Intended Audience :: Developers
Classifier: License :: OSI Approved :: MIT License
Classifier: Operating System :: Unix
Classifier: Programming Language :: C
Classifier: Programming Language :: Python :: 3
Classifier: Topic :: Software Development :: Libraries :: Python Modules
